hesburgh/__init__.py
hesburgh/heslog.py
hesburgh/hestest.py
hesburgh/hesutil.py
hesburgh/scriptutil.py
hesburgh/secretFiles.py
hesburgh/testdata/accounts.json
hesburgh_utilities-3.0.4.dist-info/METADATA
hesburgh_utilities-3.0.4.dist-info/WHEEL
hesburgh_utilities-3.0.4.dist-info/entry_points.txt
hesburgh_utilities-3.0.4.dist-info/top_level.txt
hesburgh_utilities-3.0.4.dist-info/RECORD
