Metadata-Version: 2.1
Name: hesburgh-utilities
Version: 3.0.4
Summary: Hesburgh Libraries Utility Modules
Home-page: https://github.com/ndlib/hesburgh_utilities
Author: Harrison Beachey
Author-email: hbeachey@nd.edu
License: Apache Software License
Keywords: Logging Testing
Platform: UNKNOWN
Classifier: Development Status :: 4 - Beta
Classifier: Intended Audience :: Developers
Classifier: Topic :: Software Development :: Libraries :: Python Modules
Classifier: License :: OSI Approved :: Apache Software License
Classifier: Programming Language :: Python :: 3.7
Requires-Dist: boto3
Requires-Dist: PyYAML
Requires-Dist: paramiko
Requires-Dist: raven
